{
  "$schema": "https://schema.management.azure.com/schemas/2019-04-01/deploymentTemplate.json#",
  "contentVersion": "1.0.0.0",
  "parameters": {
    "aksResourceId": {
      "type": "string",
      "metadata": {
        "description": "AKS Cluster Resource ID"
      }
    },
    "workspaceResourceId": {
      "type": "string",
      "metadata": {
        "description": "Azure Monitor Log Analytics Resource ID"
      }
    }
  },
  "resources": [
    {
      "name": "[split(parameters('aksResourceId'),'/')[8]]",
      "type": "Microsoft.ContainerService/managedClusters",
      "location": "[resourceGroup().location]",
      "apiVersion": "2018-03-31",
      "properties": {
        "mode": "Incremental",
        "id": "[parameters('aksResourceId')]",
        "addonProfiles": {
          "omsagent": {
            "enabled": true,
            "config": {
              "logAnalyticsWorkspaceResourceID": "[parameters('workspaceResourceId')]"
            }
          }
        }
      }
    }
  ]
}